{
    "list": [
        {
            "path": "/vue",
            "name": "vue",
            "children": [
                {
                    "path": "/a",
                    "title": "a"
                },
                {
                    "path": "/websocket",
                    "title": "websocket"
                }
            ]
        },
        {
            "path": "/react",
            "name": "react",
            "children": [
                {
                    "path": "/b",
                    "title": "b"
                }
            ]
        },
        {
            "path": "/echarts",
            "name": "ECharts"
        },
        {
            "path": "/3D",
            "name": "3D",
            "children": [
                {
                    "path": "/card",
                    "title": "card"
                }
            ]
        },
        {
            "path": "/opacity",
            "name": "opacity"
        },
        {
            "path": "/demo",
            "name": "demo"
        },
        {
            "path": "/BlurEffect",
            "name": "BlurEffect"
        },
        {
            "path": "/sride",
            "name": "sride"
        },
        {
            "path": "/run",
            "name": "run"
        },
        {
            "path": "/hover",
            "name": "hover"
        },
        {
            "path": "/Sudoku",
            "name": "Sudoku"
        },
        {
            "path": "/rgba",
            "name": "rgba"
        },
        {
            "path": "/roundTurntable",
            "name": "王者荣耀轮盘抽奖"
        },
        {
            "path": "/speak",
            "name": "朗读功能"
        },
        {
            "path": "/playingcards",
            "name": "窗口通信"
        },
        {
            "path": "/weather",
            "name": "天气预报"
        },
        {
            "path": "/network",
            "name": "实时网络监控"
        },
        {
            "path": "/webRtc",
            "name": "Vue-WebRTC"
        },
        {
            "path": "/verificationCode",
            "name": "验证码"
        }
    ]
}
